mycelyso_inspector/__init__.py
mycelyso_inspector/__main__.py
mycelyso_inspector/inspector.py
mycelyso_inspector/fetcher/__init__.py
mycelyso_inspector/fetcher/__main__.py
mycelyso_inspector/static/bower.json
mycelyso_inspector/static/index.htm
mycelyso_inspector/static/mycelyso.svg
mycelyso_inspector/static/script.js
mycelyso_inspector/static/bower_components/angular/.bower.json
mycelyso_inspector/static/bower_components/angular/LICENSE.md
mycelyso_inspector/static/bower_components/angular/README.md
mycelyso_inspector/static/bower_components/angular/angular-csp.css
mycelyso_inspector/static/bower_components/angular/angular.js
mycelyso_inspector/static/bower_components/angular/angular.min.js
mycelyso_inspector/static/bower_components/angular/angular.min.js.gzip
mycelyso_inspector/static/bower_components/angular/angular.min.js.map
mycelyso_inspector/static/bower_components/angular/bower.json
mycelyso_inspector/static/bower_components/angular/index.js
mycelyso_inspector/static/bower_components/angular/package.json
mycelyso_inspector/static/bower_components/angular-ui-grid/.bower.json
mycelyso_inspector/static/bower_components/angular-ui-grid/CHANGELOG.md
mycelyso_inspector/static/bower_components/angular-ui-grid/README.md
mycelyso_inspector/static/bower_components/angular-ui-grid/bower.json
mycelyso_inspector/static/bower_components/angular-ui-grid/index.js
mycelyso_inspector/static/bower_components/angular-ui-grid/package.json
mycelyso_inspector/static/bower_components/angular-ui-grid/ui-grid.css
mycelyso_inspector/static/bower_components/angular-ui-grid/ui-grid.eot
mycelyso_inspector/static/bower_components/angular-ui-grid/ui-grid.js
mycelyso_inspector/static/bower_components/angular-ui-grid/ui-grid.min.css
mycelyso_inspector/static/bower_components/angular-ui-grid/ui-grid.min.js
mycelyso_inspector/static/bower_components/angular-ui-grid/ui-grid.svg
mycelyso_inspector/static/bower_components/angular-ui-grid/ui-grid.ttf
mycelyso_inspector-1.0.0.dist-info/LICENSE
mycelyso_inspector-1.0.0.dist-info/METADATA
mycelyso_inspector-1.0.0.dist-info/WHEEL
mycelyso_inspector-1.0.0.dist-info/top_level.txt
mycelyso_inspector-1.0.0.dist-info/RECORD
