Metadata-Version: 2.1
Name: mycelyso-inspector
Version: 1.0.0
Summary: MYCElium anaLYsis SOftware - Inspector
Home-page: https://github.com/modsim/mycelyso
Author: Christian C. Sachs
Author-email: c.sachs@fz-juelich.de
License: BSD
Platform: UNKNOWN
Classifier: Development Status :: 4 - Beta
Classifier: Environment :: Console
Classifier: Intended Audience :: Science/Research
Classifier: License :: OSI Approved :: BSD License
Classifier: Operating System :: POSIX
Classifier: Operating System :: POSIX :: Linux
Classifier: Operating System :: MacOS :: MacOS X
Classifier: Operating System :: Microsoft :: Windows
Classifier: Programming Language :: Python :: 3
Classifier: Programming Language :: Python :: 3.6
Classifier: Topic :: Scientific/Engineering :: Bio-Informatics
Classifier: Topic :: Scientific/Engineering :: Image Recognition
Requires-Dist: numpy
Requires-Dist: scipy
Requires-Dist: matplotlib
Requires-Dist: mpld3
Requires-Dist: pandas
Requires-Dist: flask
Requires-Dist: networkx
Requires-Dist: purepng
